rocauc_comparison/__init__.py
rocauc_comparison/delong.py
rocauc_comparison-0.1.dist-info/METADATA
rocauc_comparison-0.1.dist-info/WHEEL
rocauc_comparison-0.1.dist-info/top_level.txt
rocauc_comparison-0.1.dist-info/RECORD
