Metadata-Version: 2.1
Name: rocauc-comparison
Version: 0.1
Summary: A package for comparing ROC AUC scores using DeLong's method.
Home-page: https://github.com/mmsa/rocauc_comparison
Author: Mohamed Mostafa
Author-email: mmsa12@gmail.com
Classifier: Programming Language :: Python :: 3
Classifier: License :: OSI Approved :: MIT License
Classifier: Operating System :: OS Independent
Requires-Python: >=3.6
Requires-Dist: numpy >=1.20.0
Requires-Dist: scipy >=1.6.0
